vhegen/__init__.py
vhegen/modules/__init__.py
vhegen/modules/electronic.py
vhegen/modules/glbls.py
vhegen/modules/input.py
vhegen/modules/output.py
vhegen/modules/vibrational.py
vhegen/tables/__init__.py
vhegen/tables/eigenvalues.py
vhegen/tables/formulas.py
vhegen/tables/matrices.py
vhegen-2.0.21.data/scripts/vhegen
vhegen-2.0.21.dist-info/LICENSE
vhegen-2.0.21.dist-info/METADATA
vhegen-2.0.21.dist-info/WHEEL
vhegen-2.0.21.dist-info/top_level.txt
vhegen-2.0.21.dist-info/RECORD
