Metadata-Version: 2.1
Name: vhegen
Version: 2.0.21
Summary: A package that generates Hamiltonians for arbitrarly large (pseudo)Jahn-Teller systems
Home-page: https://github.com/T-Zeng-Group-TheoChem-YorkU/vhegen
Author: James Brown
Author-email: jbrown88@yorku.ca
License: UNKNOWN
Project-URL: Bug Tracker, https://github.com/T-Zeng-Group-TheoChem-YorkU/vhegen/issues
Platform: UNKNOWN
Classifier: Programming Language :: Python :: 3
Classifier: License :: OSI Approved :: MIT License
Classifier: Operating System :: OS Independent
Requires-Python: >=3.6
Requires-Dist: numpy
Requires-Dist: sympy
